{"n":110,"name":"An-Nasr","meaning":"Divine Support","arabic":"النَّصۡرِ","ayahs":3,"type":"Medinan","verses":[{"n":1,"ar":"إِذَا جَآءَ نَصْرُ ٱللَّهِ وَٱلْفَتْحُ","ru":"Когда придет помощь Аллаха и настанет победа,","kk":"Ей, Мұхаммед! Аллаһтың көмегі және жеңіс келген кезде\r","en":"When the victory of Allah has come and the conquest,","tr":"Iza jaa-a nas rullahi walfath"},{"n":2,"ar":"وَرَأَيْتَ ٱلنَّاسَ يَدْخُلُونَ فِى دِينِ ٱللَّهِ أَفْوَاجًۭا","ru":"когда ты увидишь, как люди толпами обращаются в религию Аллаха,","kk":"әрі адамдардың Аллаһтың дініне топ-тобымен кіргенін көргеніңде\r","en":"And you see the people entering into the religion of Allah in multitudes,","tr":"Wa ra-aitan naasa yadkhuloona fee deenil laahi afwajah"},{"n":3,"ar":"فَسَبِّحْ بِحَمْدِ رَبِّكَ وَٱسْتَغْفِرْهُ ۚ إِنَّهُۥ كَانَ تَوَّابًۢا","ru":"восславь же хвалой Господа своего и попроси у Него прощения. Воистину, Он - Принимающий покаяния.","kk":"Раббыңды мақтаулар айтып дәріпте және Одан кешірім тіле. Ол тәубені істеген күнәсіне шынайы өкініп, Оғанбойсұнуғақайтуды Қабыл етуші\r","en":"Then exalt [Him] with praise of your Lord and ask forgiveness of Him. Indeed, He is ever Accepting of repentance.","tr":"Fa sab bih bihamdi rabbika was taghfir, innahu kaana tawwaaba"}]}